ament_cmake_export_definitions/_dummy.cpython-314-x86_64-linux-gnu.so
ros_ament_cmake_export_definitions-2.7.3.data/data/share/ament_cmake_export_definitions/local_setup.bash
ros_ament_cmake_export_definitions-2.7.3.data/data/share/ament_cmake_export_definitions/local_setup.dsv
ros_ament_cmake_export_definitions-2.7.3.data/data/share/ament_cmake_export_definitions/local_setup.sh
ros_ament_cmake_export_definitions-2.7.3.data/data/share/ament_cmake_export_definitions/local_setup.zsh
ros_ament_cmake_export_definitions-2.7.3.data/data/share/ament_cmake_export_definitions/package.dsv
ros_ament_cmake_export_definitions-2.7.3.data/data/share/ament_cmake_export_definitions/package.xml
ros_ament_cmake_export_definitions-2.7.3.data/data/share/ament_cmake_export_definitions/cmake/ament_cmake_export_definitions-extras.cmake
ros_ament_cmake_export_definitions-2.7.3.data/data/share/ament_cmake_export_definitions/cmake/ament_cmake_export_definitions-extras.cmake.in
ros_ament_cmake_export_definitions-2.7.3.data/data/share/ament_cmake_export_definitions/cmake/ament_cmake_export_definitionsConfig-version.cmake
ros_ament_cmake_export_definitions-2.7.3.data/data/share/ament_cmake_export_definitions/cmake/ament_cmake_export_definitionsConfig.cmake
ros_ament_cmake_export_definitions-2.7.3.data/data/share/ament_cmake_export_definitions/cmake/ament_cmake_export_definitions_package_hook.cmake
ros_ament_cmake_export_definitions-2.7.3.data/data/share/ament_cmake_export_definitions/cmake/ament_export_definitions.cmake
ros_ament_cmake_export_definitions-2.7.3.data/data/share/ament_cmake_export_definitions/environment/ament_prefix_path.dsv
ros_ament_cmake_export_definitions-2.7.3.data/data/share/ament_cmake_export_definitions/environment/ament_prefix_path.sh
ros_ament_cmake_export_definitions-2.7.3.data/data/share/ament_cmake_export_definitions/environment/path.dsv
ros_ament_cmake_export_definitions-2.7.3.data/data/share/ament_cmake_export_definitions/environment/path.sh
ros_ament_cmake_export_definitions-2.7.3.dist-info/METADATA
ros_ament_cmake_export_definitions-2.7.3.dist-info/WHEEL
ros_ament_cmake_export_definitions-2.7.3.dist-info/top_level.txt
ros_ament_cmake_export_definitions-2.7.3.dist-info/RECORD
